Metadata-Version: 2.1
Name: even-tester
Version: 0.0.2
Summary: A python library by srb
Home-page: http://github.com/srbcheema2/even_tester
Author: Sarbjit Singh
Author-email: srbcheema2@gmail.com
License: MIT License
Platform: UNKNOWN
Classifier: Operating System :: POSIX :: Linux
Classifier: License :: OSI Approved :: MIT License
Classifier: Programming Language :: Python :: 3.5
